sk_schemas/__init__.py
sk_schemas/acl.py
sk_schemas/auth.py
sk_schemas/certs.py
sk_schemas/crypto.py
sk_schemas/inet.py
sk_schemas/intf.py
sk_schemas/ipsec.py
sk_schemas/stats.py
sk_schemas/sys.py
sk_schemas/users.py
sk_schemas-2.4.2.dist-info/METADATA
sk_schemas-2.4.2.dist-info/WHEEL
sk_schemas-2.4.2.dist-info/licenses/LICENSE.md
sk_schemas-2.4.2.dist-info/RECORD
